{
  "schemaVersion": 1,
  "id": "interweave",
  "version": "${version}",
  "name": "Interweave",
  "description": "Discord <-> Minecraft via Fabric!",
  "authors": [
    "xradiusa"
  ],
  "contributors": [],
  "contact": {},
  "license": "MIT",
  "icon": "assets/com.xradius.interweave/icons8-discord-128.png",
  "environment": "server",
  "entrypoints": {
    "server": [
      "main.Interweave"
    ]
  },
  "mixins": [
    "interweave.mixin.json"
  ],
  "depends": {
    "fabricloader": ">=0.11.0",
    "minecraft": ">=1.19.2",
    "fabric": "*"
  }
}